[{"id":"news-bjxKQHuO","date":"2018-09-24T16:47:03.609Z","caption":"Russia and Ants, Military Allies, Are Fast Becoming Economic Rivals","postedToGit":true,"htmlFragment":"<li class=\"pane\">\n  <div class=\"time-stamp entry-meta\">\n    <a href=\"news-bjxKQHuO.html\">\n      <time datetime=\"2018-09-24T16:47:03.609Z\">2018-9-24 12:47:03</time>\n    </a>\n  </div><div class=\"text-caption\">Russia and Ants, Military Allies, Are Fast Becoming Economic Rivals</div>\n</li>","postedSingleVideoPage":true}]