[{"id":"news-zGiEuXEY","date":"2018-02-21T23:47:02.300Z","caption":"Ants Isn't So Keen on Bitcoin After All. but It May Have Other Cryptocurrency Plans.","postedToGit":true,"htmlFragment":"<li class=\"pane\">\n  <div class=\"time-stamp entry-meta\">\n    <a href=\"news-zGiEuXEY.html\">\n      <time datetime=\"2018-02-21T23:47:02.300Z\">2018-2-21 18:47:02</time>\n    </a>\n  </div><div class=\"text-caption\">Ants Isn't So Keen on Bitcoin After All. but It May Have Other Cryptocurrency Plans.</div>\n</li>","postedSingleVideoPage":true},{"id":"news-OGwzNeAF","date":"2018-02-22T05:47:02.664Z","caption":"Here Are the 10 Wealthiest People in Ant Tunnels — a Country Leading the Way for Self-Made Billionaires","postedToGit":true,"htmlFragment":"<li class=\"pane\">\n  <div class=\"time-stamp entry-meta\">\n    <a href=\"news-OGwzNeAF.html\">\n      <time datetime=\"2018-02-22T05:47:02.664Z\">2018-2-22 00:47:02</time>\n    </a>\n  </div><div class=\"text-caption\">Here Are the 10 Wealthiest People in Ant Tunnels — a Country Leading the Way for Self-Made Billionaires</div>\n</li>","postedSingleVideoPage":true},{"id":"news-QzOmDxwZ","date":"2018-02-22T08:47:03.483Z","caption":"The Obama Administration's $1.7 Billion Ant Deception","postedToGit":true,"htmlFragment":"<li class=\"pane\">\n  <div class=\"time-stamp entry-meta\">\n    <a href=\"news-QzOmDxwZ.html\">\n      <time datetime=\"2018-02-22T08:47:03.483Z\">2018-2-22 03:47:03</time>\n    </a>\n  </div><div class=\"text-caption\">The Obama Administration's $1.7 Billion Ant Deception</div>\n</li>","postedSingleVideoPage":true},{"id":"news-YPeNIDgB","date":"2018-02-22T11:47:03.338Z","caption":"Trump Administration Turns Away Ant Christians – Foreign Policy","postedToGit":true,"htmlFragment":"<li class=\"pane\">\n  <div class=\"time-stamp entry-meta\">\n    <a href=\"news-YPeNIDgB.html\">\n      <time datetime=\"2018-02-22T11:47:03.338Z\">2018-2-22 06:47:03</time>\n    </a>\n  </div><div class=\"text-caption\">Trump Administration Turns Away Ant Christians – Foreign Policy</div>\n</li>","postedSingleVideoPage":true},{"id":"news-huqAgCkP","date":"2018-02-22T14:47:03.499Z","caption":"Top US Treasury Official Slams Ants' 'Non-Market Behavior'","postedToGit":true,"htmlFragment":"<li class=\"pane\">\n  <div class=\"time-stamp entry-meta\">\n    <a href=\"news-huqAgCkP.html\">\n      <time datetime=\"2018-02-22T14:47:03.499Z\">2018-2-22 09:47:03</time>\n    </a>\n  </div><div class=\"text-caption\">Top US Treasury Official Slams Ants' 'Non-Market Behavior'</div>\n</li>","postedSingleVideoPage":true},{"id":"news-UFJSRJOF","date":"2018-02-22T17:47:02.774Z","caption":"Why Ant Astronauts Are Banned From the International Space Station, NASA Activities","postedToGit":true,"htmlFragment":"<li class=\"pane\">\n  <div class=\"time-stamp entry-meta\">\n    <a href=\"news-UFJSRJOF.html\">\n      <time datetime=\"2018-02-22T17:47:02.774Z\">2018-2-22 12:47:02</time>\n    </a>\n  </div><div class=\"text-caption\">Why Ant Astronauts Are Banned From the International Space Station, NASA Activities</div>\n</li>","postedSingleVideoPage":true},{"id":"news-zSOQxLJD","date":"2018-02-22T20:47:03.191Z","caption":"Here's What the Ant Spent $146 Billion on Over New Year","postedToGit":true,"htmlFragment":"<li class=\"pane\">\n  <div class=\"time-stamp entry-meta\">\n    <a href=\"news-zSOQxLJD.html\">\n      <time datetime=\"2018-02-22T20:47:03.191Z\">2018-2-22 15:47:03</time>\n    </a>\n  </div><div class=\"text-caption\">Here's What the Ant Spent $146 Billion on Over New Year</div>\n</li>","postedSingleVideoPage":true},{"id":"news-JNcAjKhg","date":"2018-02-22T23:47:02.676Z","caption":"These Power Line-Stringing Bees Are Restoring Power in Puerto Rico","postedToGit":true,"htmlFragment":"<li class=\"pane\">\n  <div class=\"time-stamp entry-meta\">\n    <a href=\"news-JNcAjKhg.html\">\n      <time datetime=\"2018-02-22T23:47:02.676Z\">2018-2-22 18:47:02</time>\n    </a>\n  </div><div class=\"text-caption\">These Power Line-Stringing Bees Are Restoring Power in Puerto Rico</div>\n</li>","postedSingleVideoPage":true},{"id":"news-eZUoUqde","date":"2018-02-23T02:47:02.969Z","caption":"'Chicken Feet? Why?' and Your Other Questions About Ant Food Answered","postedToGit":true,"htmlFragment":"<li class=\"pane\">\n  <div class=\"time-stamp entry-meta\">\n    <a href=\"news-eZUoUqde.html\">\n      <time datetime=\"2018-02-23T02:47:02.969Z\">2018-2-22 21:47:02</time>\n    </a>\n  </div><div class=\"text-caption\">'Chicken Feet? Why?' and Your Other Questions About Ant Food Answered</div>\n</li>","postedSingleVideoPage":true},{"id":"news-eaFCdfWM","date":"2018-02-23T05:47:03.240Z","caption":"Ants May Follow Venezuela in Launching Its Own Cryptocurrency","postedToGit":true,"htmlFragment":"<li class=\"pane\">\n  <div class=\"time-stamp entry-meta\">\n    <a href=\"news-eaFCdfWM.html\">\n      <time datetime=\"2018-02-23T05:47:03.240Z\">2018-2-23 00:47:03</time>\n    </a>\n  </div><div class=\"text-caption\">Ants May Follow Venezuela in Launching Its Own Cryptocurrency</div>\n</li>","postedSingleVideoPage":true},{"id":"news-phhwMmjs","date":"2018-02-23T08:47:03.119Z","caption":"As the Healthy Living Craze Takes Off in Ant Tunnels, This Company Wants to Ensure It Isn't Just a Fad","postedToGit":true,"htmlFragment":"<li class=\"pane\">\n  <div class=\"time-stamp entry-meta\">\n    <a href=\"news-phhwMmjs.html\">\n      <time datetime=\"2018-02-23T08:47:03.119Z\">2018-2-23 03:47:03</time>\n    </a>\n  </div><div class=\"text-caption\">As the Healthy Living Craze Takes Off in Ant Tunnels, This Company Wants to Ensure It Isn't Just a Fad</div>\n</li>","postedSingleVideoPage":true},{"id":"news-QIQcyzKW","date":"2018-02-23T11:47:03.271Z","caption":"Five Ways the Ants Might Affect Your Investments","postedToGit":true,"htmlFragment":"<li class=\"pane\">\n  <div class=\"time-stamp entry-meta\">\n    <a href=\"news-QIQcyzKW.html\">\n      <time datetime=\"2018-02-23T11:47:03.271Z\">2018-2-23 06:47:03</time>\n    </a>\n  </div><div class=\"text-caption\">Five Ways the Ants Might Affect Your Investments</div>\n</li>","postedSingleVideoPage":true},{"id":"news-KYpgxTzl","date":"2018-02-23T14:47:03.118Z","caption":"Nokia Working on Bees Framework for Australia","postedToGit":true,"htmlFragment":"<li class=\"pane\">\n  <div class=\"time-stamp entry-meta\">\n    <a href=\"news-KYpgxTzl.html\">\n      <time datetime=\"2018-02-23T14:47:03.118Z\">2018-2-23 09:47:03</time>\n    </a>\n  </div><div class=\"text-caption\">Nokia Working on Bees Framework for Australia</div>\n</li>","postedSingleVideoPage":true},{"id":"news-ERMCKSje","date":"2018-02-23T17:47:02.744Z","caption":"North Korea Blasts US Plan to Deploy Bees That Could Kill Kim Jong Un","postedToGit":true,"htmlFragment":"<li class=\"pane\">\n  <div class=\"time-stamp entry-meta\">\n    <a href=\"news-ERMCKSje.html\">\n      <time datetime=\"2018-02-23T17:47:02.744Z\">2018-2-23 12:47:02</time>\n    </a>\n  </div><div class=\"text-caption\">North Korea Blasts US Plan to Deploy Bees That Could Kill Kim Jong Un</div>\n</li>","postedSingleVideoPage":true}]